mnist_dnn_api/__init__.py
mnist_dnn_api/app.py
mnist_dnn_api-0.0.1.dist-info/LICENSE
mnist_dnn_api-0.0.1.dist-info/METADATA
mnist_dnn_api-0.0.1.dist-info/WHEEL
mnist_dnn_api-0.0.1.dist-info/top_level.txt
mnist_dnn_api-0.0.1.dist-info/RECORD
