Metadata-Version: 2.1
Name: mnist-dnn-api
Version: 0.0.1
Summary: API Server for MNIST_DNN package
Home-page: https://github.com/fedele7008/MNIST_DNN
Author: John Yoon
Author-email: fedelejohn7008@gmail.com
Project-URL: Issue Tracker, https://github.com/fedele7008/MNIST_DNN/issues
Project-URL: Wiki, https://github.com/fedele7008/MNIST_DNN/wiki
Classifier: Programming Language :: Python :: 3
Classifier: Programming Language :: Python :: 3.6
Classifier: Programming Language :: Python :: 3.11
Classifier: License :: OSI Approved :: MIT License
Requires-Python: >=3.6
License-File: LICENSE
Requires-Dist: click (==8.1.3)
Requires-Dist: Flask (==2.2.2)
Requires-Dist: itsdangerous (==2.1.2)
Requires-Dist: Jinja2 (==3.1.2)
Requires-Dist: MarkupSafe (==2.1.2)
Requires-Dist: Werkzeug (==2.2.2)
